envisor/__init__.py
envisor/env.py
envisor-0.1.1.dist-info/METADATA
envisor-0.1.1.dist-info/WHEEL
envisor-0.1.1.dist-info/licenses/LICENSE
envisor-0.1.1.dist-info/RECORD
