Metadata-Version: 2.1
Name: envisor
Version: 0.1.1
Summary: A Python package for working with environment variables.
Project-URL: Homepage, https://github.com/Abstract-X/envisor
Project-URL: Bug Tracker, https://github.com/Abstract-X/envisor/issues
Author-email: Abstract-X <abstract-x-mail@protonmail.com>
License: MIT License
License-File: LICENSE
Classifier: License :: OSI Approved :: MIT License
Classifier: Operating System :: OS Independent
Classifier: Programming Language :: Python :: 3
Requires-Python: >=3.6
